mhi/pscad/__init__.py
mhi/pscad/__main__.py
mhi/pscad/annotation.py
mhi/pscad/buildtime.py
mhi/pscad/canvas.py
mhi/pscad/certificate.py
mhi/pscad/compiler.py
mhi/pscad/component.py
mhi/pscad/control.py
mhi/pscad/definition.py
mhi/pscad/form.py
mhi/pscad/graph.py
mhi/pscad/graphics.py
mhi/pscad/handler.py
mhi/pscad/instrument.py
mhi/pscad/parameter_grid.py
mhi/pscad/project.py
mhi/pscad/pscad.py
mhi/pscad/py.typed
mhi/pscad/remote.py
mhi/pscad/resource.py
mhi/pscad/simset.py
mhi/pscad/types.py
mhi/pscad/unit.py
mhi/pscad/wizard.py
mhi/pscad/html/changes.html
mhi/pscad/html/genindex.html
mhi/pscad/html/index.html
mhi/pscad/html/objects.inv
mhi/pscad/html/py-modindex.html
mhi/pscad/html/quick_start.html
mhi/pscad/html/search.html
mhi/pscad/html/searchindex.js
mhi/pscad/html/upgrading.html
mhi/pscad/html/_downloads/111b16be446e2f465be14302078cdad0/step-13.py
mhi/pscad/html/_downloads/13ad2159fd3d8cfad2e1980cd1fc0ed1/step-06.py
mhi/pscad/html/_downloads/253f5cc6ac49d440294bba3e1bc3321c/settings.py
mhi/pscad/html/_downloads/2cec8b7562522a99a8fccce5f5877d6b/step-10.py
mhi/pscad/html/_downloads/328435b5bab37e21e66a548ce33e48ee/step-00.py
mhi/pscad/html/_downloads/38a9bed193a9dbb7bd983102dfb6bbd0/step-02.py
mhi/pscad/html/_downloads/4bf80f8ca53bd75c4279ae78ca72fa22/step-07.py
mhi/pscad/html/_downloads/5f8e7d605abf2685990b982425f748de/quick_start.py
mhi/pscad/html/_downloads/70bfc67eba56e194f90aa8e44d13f75a/step-04.py
mhi/pscad/html/_downloads/725f547e1dece6174b70156bb4742c84/step-03.py
mhi/pscad/html/_downloads/87de6810b4beaf6d0f3014b0cbe5e9fa/step-09.py
mhi/pscad/html/_downloads/9421c324e319e4792d7f4e9ee868458c/step-06a.py
mhi/pscad/html/_downloads/9edd20e05a927072698668bde6bdb8c1/step-14.py
mhi/pscad/html/_downloads/a716f6927206eec2a2864d524c8a43a4/step-20.py
mhi/pscad/html/_downloads/bbe0919cc79b1f67eaaa7325234caad7/step-08.py
mhi/pscad/html/_downloads/c79996154c27eab86a26f2b347a00167/step-12.py
mhi/pscad/html/_downloads/cd8026a5775ab40b3e97c4be604c5f63/step-21.py
mhi_pscad-3.0.10.dist-info/licenses/LICENSE
mhi_pscad-3.0.10.dist-info/METADATA
mhi_pscad-3.0.10.dist-info/WHEEL
mhi_pscad-3.0.10.dist-info/top_level.txt
mhi_pscad-3.0.10.dist-info/RECORD
