Metadata-Version: 2.4
Name: mhi-pscad
Version: 3.0.10
Summary: Manitoba Hydro International: PSCAD Automation library
Author-email: "Manitoba Hydro International Ltd." <pscad@mhi.ca>
License-Expression: BSD-3-Clause-Clear
Project-URL: Homepage, https://www.pscad.com/support/support-resources
Project-URL: Documentation, https://www.pscad.com/webhelp-v502-al/index.html
Classifier: Development Status :: 5 - Production/Stable
Classifier: Programming Language :: Python :: 3
Classifier: Programming Language :: Python :: 3.7
Classifier: Programming Language :: Python :: 3.8
Classifier: Programming Language :: Python :: 3.9
Classifier: Programming Language :: Python :: 3.10
Classifier: Programming Language :: Python :: 3.11
Classifier: Programming Language :: Python :: 3.12
Classifier: Programming Language :: Python :: 3.13
Classifier: Operating System :: Microsoft :: Windows
Requires-Python: >=3.7
License-File: LICENSE
Requires-Dist: mhi.common<4,>=3.1.5
Provides-Extra: cosim
Requires-Dist: mhi.cosim; extra == "cosim"
Provides-Extra: psout
Requires-Dist: mhi.psout; extra == "psout"
Provides-Extra: xml
Requires-Dist: mhi.xml; extra == "xml"
Provides-Extra: all
Requires-Dist: mhi.cosim; extra == "all"
Requires-Dist: mhi.psout; extra == "all"
Requires-Dist: mhi.xml; extra == "all"
Dynamic: license-file
